dvars/__init__.py
dvars/apsaplot.py
dvars/dars/__init__.py
dvars/dars/dars.py
dvars/dars/libdars_win32.pyd
dvars-0.1.6.dist-info/licenses/AUTHORS.txt
dvars-0.1.6.dist-info/licenses/LICENCE.txt
dvars-0.1.6.dist-info/METADATA
dvars-0.1.6.dist-info/WHEEL
dvars-0.1.6.dist-info/top_level.txt
dvars-0.1.6.dist-info/RECORD
