Metadata-Version: 2.4
Name: dvars
Version: 0.1.6
Summary: Response spectra calculations for earthquake engineering
Author-email: Pavel Zacherle <zapa@ipe.muni.cz>
License-Expression: MIT
Project-URL: Repository, https://github.com/ipemu/dvars.git
Project-URL: Issues, https://github.com/ipemu/dvars/issues
Keywords: response spectra,earthquake engineering
Classifier: Development Status :: 3 - Alpha
Classifier: Programming Language :: Python
Classifier: Programming Language :: Python :: 3
Classifier: Programming Language :: C
Classifier: Topic :: Scientific/Engineering
Classifier: Intended Audience :: Developers
Classifier: Operating System :: POSIX :: Linux
Classifier: Operating System :: Microsoft :: Windows
Requires-Python: >=3.4
License-File: LICENCE.txt
License-File: AUTHORS.txt
Requires-Dist: numpy
Requires-Dist: matplotlib
Dynamic: license-file
